README.md
setup.py
unit_identification/__init__.py
unit_identification/classes.py
unit_identification/classifier.py
unit_identification/disambiguate.py
unit_identification/entities.json
unit_identification/language.py
unit_identification/load.py
unit_identification/no_classifier.py
unit_identification/parser.py
unit_identification/regex.py
unit_identification/speak.py
unit_identification/units.json
unit_identification.egg-info/PKG-INFO
unit_identification.egg-info/SOURCES.txt
unit_identification.egg-info/dependency_links.txt
unit_identification.egg-info/requires.txt
unit_identification.egg-info/top_level.txt
unit_identification/_lang/__init__.py
unit_identification/_lang/en_US/__init__.py
unit_identification/_lang/en_US/classifier.py
unit_identification/_lang/en_US/clf.joblib
unit_identification/_lang/en_US/common-words.json
unit_identification/_lang/en_US/entities.json
unit_identification/_lang/en_US/load.py
unit_identification/_lang/en_US/parser.py
unit_identification/_lang/en_US/regex.py
unit_identification/_lang/en_US/speak.py
unit_identification/_lang/en_US/units.json
unit_identification/_lang/en_US/tests/__init__.py
unit_identification/_lang/en_US/tests/extract_spellout_values.py
unit_identification/_lang/en_US/train/__init__.py
unit_identification/_lang/en_US/train/similars.json
unit_identification/_lang/en_US/train/train.json
unit_identification/_lang/en_US/train/wiki.json