Metadata-Version: 2.1
Name: unit-identification
Version: 3.6
Summary: UOM identification
Home-page: https://github.com/ExpertOfAI/unit_identification
Author: ExpertOfAI
License: MIT
Classifier: Programming Language :: Python :: 3
Classifier: License :: OSI Approved :: MIT License
Classifier: Operating System :: OS Independent
Requires-Python: >=3.6
